{
    "data": [
        {
            "id": "player1",
            "owner": { "SingleOwner": "receiverAddress" },
            "category": "object",
            "version": "6",
            "readonly": "false",
            "objType": "0x2::Example::Player",
            "data": {
                "contents": {
                    "earth_runes_count": 4,
                    "fire_runes_count": 2,
                    "water_runes_count": 1,
                    "wind_runes_count": 8,
                    "id": {},
                    "owned_standalone_id": {},
                    "owned_collections_id": { "vec": [] },
                    "player_name": {
                        "bytes": [
                            84, 101, 115, 116, 32, 80, 108, 97, 121, 101, 114
                        ]
                    }
                }
            }
        },
        {
            "id": "player2",
            "owner": { "SingleOwner": "receiverAddress" },
            "category": "object",
            "version": "5",
            "readonly": "false",
            "objType": "0x2::Example::Player",
            "data": {
                "contents": {
                    "earth_runes_count": 1,
                    "fire_runes_count": 10,
                    "water_runes_count": 3,
                    "wind_runes_count": 2,
                    "id": {},
                    "player_name": {
                        "bytes": [
                            84, 101, 115, 116, 32, 80, 108, 97, 121, 101, 114
                        ]
                    },
                    "owned_standalone_id": {
                        "bytes": "standaloneObject"
                    },
                    "owned_collections_id": {
                        "vec": [
                            {
                                "bytes": "CollectionObject"
                            }
                        ]
                    }
                }
            }
        },
        {
            "id": "player0",
            "owner": { "SingleOwner": "" },
            "category": "object",
            "version": "100",
            "readonly": "false",
            "objType": "0x2::Example::Player",
            "data": {
                "contents": {
                    "earth_runes_count": 1,
                    "fire_runes_count": 10,
                    "water_runes_count": 3,
                    "wind_runes_count": 2,
                    "id": {},
                    "player_name": {
                        "bytes": [
                            84, 101, 115, 116, 32, 80, 108, 97, 121, 101, 114
                        ]
                    }
                }
            }
        },
        {
            "id": "player3",
            "owner": { "SingleOwner": "" },
            "category": "object",
            "version": "100",
            "readonly": "false",
            "objType": "0x2::Example::Player",
            "data": {
                "contents": {
                    "earth_runes_count": 1,
                    "fire_runes_count": 10,
                    "water_runes_count": 3,
                    "wind_runes_count": 2,
                    "id": {},
                    "player_name": {
                        "bytes": [
                            84, 101, 115, 116, 32, 80, 108, 97, 121, 101, 114
                        ]
                    }
                }
            }
        },
        {
            "id": "player4",
            "owner": { "SingleOwner": "" },
            "category": "object",
            "version": "100",
            "readonly": "false",
            "objType": "0x2::Example::Player",
            "data": {
                "contents": {
                    "earth_runes_count": 1,
                    "fire_runes_count": 10,
                    "water_runes_count": 3,
                    "wind_runes_count": 2,
                    "id": {},
                    "player_name": {
                        "bytes": [
                            84, 101, 115, 116, 32, 80, 108, 97, 121, 101, 114
                        ]
                    }
                }
            }
        },
        {
            "id": "player5",
            "owner": { "SingleOwner": "" },
            "category": "object",
            "version": "100",
            "readonly": "false",
            "objType": "0x2::Example::Player",
            "data": {
                "contents": {
                    "earth_runes_count": 1,
                    "fire_runes_count": 10,
                    "water_runes_count": 3,
                    "wind_runes_count": 2,
                    "id": {},
                    "player_name": {
                        "bytes": [
                            84, 101, 115, 116, 32, 80, 108, 97, 121, 101, 114
                        ]
                    }
                }
            }
        },
        {
            "id": "player6",
            "owner": { "SingleOwner": "" },
            "category": "object",
            "version": "100",
            "readonly": "false",
            "objType": "0x2::Example::Player",
            "data": {
                "contents": {
                    "earth_runes_count": 1,
                    "fire_runes_count": 10,
                    "water_runes_count": 3,
                    "wind_runes_count": 2,
                    "id": {},
                    "player_name": {
                        "bytes": [
                            84, 101, 115, 116, 32, 80, 108, 97, 121, 101, 114
                        ]
                    }
                }
            }
        },
        {
            "id": "player7",
            "owner": { "SingleOwner": "" },
            "category": "object",
            "version": "100",
            "readonly": "false",
            "objType": "0x2::Example::Player",
            "data": {
                "contents": {
                    "earth_runes_count": 1,
                    "fire_runes_count": 10,
                    "water_runes_count": 3,
                    "wind_runes_count": 2,
                    "id": {},
                    "player_name": {
                        "bytes": [
                            84, 101, 115, 116, 32, 80, 108, 97, 121, 101, 114
                        ]
                    }
                }
            }
        },
        {
            "id": "player8",
            "owner": { "SingleOwner": "" },
            "category": "object",
            "version": "100",
            "readonly": "false",
            "objType": "0x2::Example::Player",
            "data": {
                "contents": {
                    "earth_runes_count": 1,
                    "fire_runes_count": 10,
                    "water_runes_count": 3,
                    "wind_runes_count": 2,
                    "id": {},
                    "player_name": {
                        "bytes": [
                            84, 101, 115, 116, 32, 80, 108, 97, 121, 101, 114
                        ]
                    }
                }
            }
        },
        {
            "id": "player9",
            "owner": { "SingleOwner": "" },
            "category": "object",
            "version": "100",
            "readonly": "false",
            "objType": "0x2::Example::Player",
            "data": {
                "contents": {
                    "earth_runes_count": 1,
                    "fire_runes_count": 10,
                    "water_runes_count": 3,
                    "wind_runes_count": 2,
                    "id": {},
                    "player_name": {
                        "bytes": [
                            84, 101, 115, 116, 32, 80, 108, 97, 121, 101, 114
                        ]
                    }
                }
            }
        },
        {
            "id": "playerA1",
            "owner": { "SingleOwner": "" },
            "category": "object",
            "version": "100",
            "readonly": "false",
            "objType": "0x2::Example::Player",
            "data": {
                "contents": {
                    "earth_runes_count": 1,
                    "fire_runes_count": 10,
                    "water_runes_count": 3,
                    "wind_runes_count": 2,
                    "id": {},
                    "player_name": {
                        "bytes": [
                            84, 101, 115, 116, 32, 80, 108, 97, 121, 101, 114
                        ]
                    }
                }
            }
        },

        {
            "id": "Image1",
            "category": "object",
            "owner": { "SingleOwner": "player2" },
            "version": "1",
            "readonly": "true",
            "objType": "0x2::Cosmetic::Plant",
            "name": "Oncidium croesus",
            "data": {
                "contents": {
                    "display": "https://sui-explorer-test-image.s3.amazonaws.com/testImage.png",
                    "cosmetic_type": 1,
                    "lore": "This is a species of orchid only found in Brazil",
                    "Humidity": "High",
                    "Temperature": "Hot",
                    "Light": "Medium",
                    "Flowering Period": "Spring to early Summer"
                }
            }
        },
        {
            "id": "Image2",
            "category": "object",
            "owner": { "SingleOwner": "CollectionObject" },
            "version": "1",
            "readonly": "true",
            "objType": "0x2::Cosmetic::Plant",
            "name": "Oncidium croesus",
            "data": {
                "contents": {
                    "display": "https://sui-explorer-test-image.s3.amazonaws.com/testImage.png",
                    "cosmetic_type": 1,
                    "lore": "This is a species of orchid only found in Brazil",
                    "Humidity": "High",
                    "Temperature": "Hot",
                    "Light": "Medium",
                    "Flowering Period": "Spring to early Summer"
                }
            }
        },
        {
            "id": "Image3",
            "category": "object",
            "owner": { "SingleOwner": "CollectionObject" },
            "version": "1",
            "readonly": "true",
            "objType": "0x2::Cosmetic::Plant",
            "name": "Oncidium croesus",
            "data": {
                "contents": {
                    "display": "https://sui-explorer-test-image.s3.amazonaws.com/testImage.png",
                    "cosmetic_type": 1,
                    "lore": "This is a species of orchid only found in Brazil",
                    "Humidity": "High",
                    "Temperature": "Hot",
                    "Light": "Medium",
                    "Flowering Period": "Spring to early Summer"
                }
            }
        },
        {
            "id": "Image4",
            "category": "object",
            "owner": { "SingleOwner": "CollectionObject" },
            "version": "1",
            "readonly": "true",
            "objType": "0x2::Cosmetic::Plant",
            "name": "Oncidium croesus",
            "data": {
                "contents": {
                    "display": "https://sui-explorer-test-image.s3.amazonaws.com/testImage.png",
                    "cosmetic_type": 1,
                    "lore": "This is a species of orchid only found in Brazil",
                    "Humidity": "High",
                    "Temperature": "Hot",
                    "Light": "Medium",
                    "Flowering Period": "Spring to early Summer"
                }
            }
        },
        {
            "id": "Image5",
            "category": "object",
            "owner": { "SingleOwner": "CollectionObject" },
            "version": "1",
            "readonly": "true",
            "objType": "0x2::Cosmetic::Plant",
            "name": "Oncidium croesus",
            "data": {
                "contents": {
                    "display": "https://sui-explorer-test-image.s3.amazonaws.com/testImage.png",
                    "cosmetic_type": 1,
                    "lore": "This is a species of orchid only found in Brazil",
                    "Humidity": "High",
                    "Temperature": "Hot",
                    "Light": "Medium",
                    "Flowering Period": "Spring to early Summer"
                }
            }
        },
        {
            "id": "Image6",
            "category": "object",
            "owner": { "SingleOwner": "CollectionObject" },
            "version": "1",
            "readonly": "true",
            "objType": "0x2::Cosmetic::Plant",
            "name": "Oncidium croesus",
            "data": {
                "contents": {
                    "display": "https://sui-explorer-test-image.s3.amazonaws.com/testImage.png",
                    "cosmetic_type": 1,
                    "lore": "This is a species of orchid only found in Brazil",
                    "Humidity": "High",
                    "Temperature": "Hot",
                    "Light": "Medium",
                    "Flowering Period": "Spring to early Summer"
                }
            }
        },
        {
            "id": "Image7",
            "category": "object",
            "owner": { "SingleOwner": "CollectionObject" },
            "version": "1",
            "readonly": "true",
            "objType": "0x2::Cosmetic::Plant",
            "name": "Oncidium croesus",
            "data": {
                "contents": {
                    "display": "https://sui-explorer-test-image.s3.amazonaws.com/testImage.png",
                    "cosmetic_type": 1,
                    "lore": "This is a species of orchid only found in Brazil",
                    "Humidity": "High",
                    "Temperature": "Hot",
                    "Light": "Medium",
                    "Flowering Period": "Spring to early Summer"
                }
            }
        },
        {
            "id": "Image8",
            "category": "object",
            "owner": { "SingleOwner": "CollectionObject" },
            "version": "1",
            "readonly": "true",
            "objType": "0x2::Cosmetic::Plant",
            "name": "Oncidium croesus",
            "data": {
                "contents": {
                    "display": "https://sui-explorer-test-image.s3.amazonaws.com/testImage.png",
                    "cosmetic_type": 1,
                    "lore": "This is a species of orchid only found in Brazil",
                    "Humidity": "High",
                    "Temperature": "Hot",
                    "Light": "Medium",
                    "Flowering Period": "Spring to early Summer"
                }
            }
        },
        {
            "id": "Image9",
            "category": "object",
            "owner": { "SingleOwner": "CollectionObject" },
            "version": "1",
            "readonly": "true",
            "objType": "0x2::Cosmetic::Plant",
            "name": "Oncidium croesus",
            "data": {
                "contents": {
                    "display": "https://sui-explorer-test-image.s3.amazonaws.com/testImage.png",
                    "cosmetic_type": 1,
                    "lore": "This is a species of orchid only found in Brazil",
                    "Humidity": "High",
                    "Temperature": "Hot",
                    "Light": "Medium",
                    "Flowering Period": "Spring to early Summer"
                }
            }
        },
        {
            "id": "Image10",
            "category": "object",
            "owner": { "SingleOwner": "CollectionObject" },
            "version": "1",
            "readonly": "true",
            "objType": "0x2::Cosmetic::Plant",
            "name": "Oncidium croesus",
            "data": {
                "contents": {
                    "display": "https://sui-explorer-test-image.s3.amazonaws.com/testImage.png",
                    "cosmetic_type": 1,
                    "lore": "This is a species of orchid only found in Brazil",
                    "Humidity": "High",
                    "Temperature": "Hot",
                    "Light": "Medium",
                    "Flowering Period": "Spring to early Summer"
                }
            }
        },
        {
            "id": "Image11",
            "category": "object",
            "owner": { "SingleOwner": "CollectionObject" },
            "version": "1",
            "readonly": "true",
            "objType": "0x2::Cosmetic::Plant",
            "name": "Oncidium croesus",
            "data": {
                "contents": {
                    "display": "https://sui-explorer-test-image.s3.amazonaws.com/testImage.png",
                    "cosmetic_type": 1,
                    "lore": "This is a species of orchid only found in Brazil",
                    "Humidity": "High",
                    "Temperature": "Hot",
                    "Light": "Medium",
                    "Flowering Period": "Spring to early Summer"
                }
            }
        },
        {
            "id": "Item1",
            "category": "object",
            "version": "1",
            "readonly": "true",
            "objType": "0x2::Cosmetic::Plant",
            "name": "Oncidium croesus",
            "data": {
                "contents": {}
            }
        },
        {
            "id": "Item2",
            "category": "object",
            "version": "1",
            "readonly": "true",
            "objType": "0x2::Cosmetic::Plant",
            "name": "Oncidium croesus",
            "data": {
                "contents": {}
            }
        },
        {
            "id": "Item3",
            "category": "object",
            "version": "1",
            "readonly": "true",
            "objType": "0x2::Cosmetic::Plant",
            "name": "Oncidium croesus",
            "data": {
                "contents": {}
            }
        },
        {
            "id": "Item4",
            "category": "object",
            "version": "1",
            "readonly": "true",
            "objType": "0x2::Cosmetic::Plant",
            "name": "Oncidium croesus",
            "data": {
                "contents": {}
            }
        },
        {
            "id": "Item5",
            "category": "object",
            "version": "1",
            "readonly": "true",
            "objType": "0x2::Cosmetic::Plant",
            "name": "Oncidium croesus",
            "data": {
                "contents": {}
            }
        },

        {
            "id": "Item6",
            "category": "object",
            "version": "1",
            "readonly": "true",
            "objType": "0x2::Cosmetic::Plant",
            "name": "Oncidium croesus",
            "data": {
                "contents": {}
            }
        },
        {
            "id": "Item7",
            "category": "object",
            "version": "1",
            "readonly": "true",
            "objType": "0x2::Cosmetic::Plant",
            "name": "Oncidium croesus",
            "data": {
                "contents": {}
            }
        },
        {
            "id": "Item8",
            "category": "object",
            "version": "1",
            "readonly": "true",
            "objType": "0x2::Cosmetic::Plant",
            "name": "Oncidium croesus",
            "data": {
                "contents": {}
            }
        },
        {
            "id": "Item9",
            "category": "object",
            "version": "1",
            "readonly": "true",
            "objType": "0x2::Cosmetic::Plant",
            "name": "Oncidium croesus",
            "data": {
                "contents": {}
            }
        },
        {
            "id": "Item10",
            "category": "object",
            "version": "1",
            "readonly": "true",
            "objType": "0x2::Cosmetic::Plant",
            "name": "Oncidium croesus",
            "data": {
                "contents": {}
            }
        },

        {
            "id": "standaloneObject",
            "category": "object",
            "owner": { "SingleOwner": "player2" },
            "version": "87",
            "readonly": "true",
            "objType": "0x2::coin::Coin<0x2::USD::USD>",
            "data": {
                "tx_digest": "Da4vHc9IwbvOYblE8LnrVsqXwryt2Kmms+xnJ7Zx5E4=",
                "contents": {
                    "id": {},
                    "balance": "9007199254740991"
                }
            }
        },
        {
            "id": "standaloneObject2",
            "category": "object",
            "owner": { "SingleOwner": "player2" },
            "version": "87",
            "readonly": "true",
            "objType": "0x2::coin::Coin<0x2::USD::USD>",
            "data": {
                "contents": {
                    "id": {},
                    "balance": "2"
                }
            }
        },
        {
            "id": "standaloneObjectSUI50",
            "category": "object",
            "owner": { "SingleOwner": "player2" },
            "version": "87",
            "readonly": "true",
            "objType": "0x2::coin::Coin<0x2::sui::SUI>",
            "data": {
                "contents": {
                    "id": {},
                    "balance": "50"
                }
            }
        },
        {
            "id": "standaloneObjectSUI150",
            "category": "object",
            "owner": { "SingleOwner": "player2" },
            "version": "87",
            "readonly": "true",
            "objType": "0x2::coin::Coin<0x2::sui::SUI>",
            "data": {
                "contents": {
                    "id": {},
                    "balance": "150"
                }
            }
        },

        {
            "id": "ProblemObject",
            "category": "object"
        },
        {
            "id": "CollectionObject",
            "category": "object",
            "owner": { "SingleOwner": "player2" },
            "version": "2",
            "readonly": "false",
            "objType": "0x2::MystenUniverse::Collection",
            "data": {
                "contents": {
                    "applied_decoration_cosmetic_0_id": {
                        "vec": [{ "bytes": "ComponentObject" }]
                    },
                    "current_xp": 0,
                    "collection_name": {
                        "bytes": [84, 101, 115, 116, 32, 70, 97, 114, 109]
                    },
                    "id": {},
                    "level": 0,
                    "lore": "Customizable with Decoration Cosmetics"
                }
            }
        },
        {
            "id": "ComponentObject",
            "category": "object",
            "owner": { "SingleOwner": "CollectionObject" },
            "version": "1",
            "readonly": "true",
            "objType": "0x2::Cosmetic::Plant",
            "name": "Oncidium croesus",
            "data": {
                "contents": {
                    "display": "https://sui-explorer-test-image.s3.amazonaws.com/testImage.png",
                    "cosmetic_type": 1,
                    "lore": "This is a species of orchid only found in Brazil",
                    "Humidity": "High",
                    "Temperature": "Hot",
                    "Light": "Medium",
                    "Flowering Period": "Spring to early Summer"
                }
            }
        },
        {
            "id": "ObjectThatOwns",
            "category": "object",
            "owner": { "SingleOwner": "CollectionObject" },
            "version": "1",
            "readonly": "true",
            "objType": "0x2::Cosmetic::Plant",
            "name": "Oncidium croesus",
            "data": {
                "contents": {
                    "display": "https://sui-explorer-test-image.s3.amazonaws.com/testImage.png",
                    "cosmetic_type": 1,
                    "lore": "This is a species of orchid only found in Brazil",
                    "Humidity": "High",
                    "Temperature": "Hot",
                    "Light": "Medium",
                    "Flowering Period": "Spring to early Summer",
                    "child_object_0_id": {
                        "vec": [
                            { "bytes": "ChildObjectWImage" },
                            { "bytes": "ChildObjectWBrokenImage" }
                        ]
                    }
                }
            }
        },
        {
            "id": "ObjectWBrokenChild",
            "category": "object",
            "owner": { "SingleOwner": "CollectionObject" },
            "version": "1",
            "readonly": "true",
            "objType": "0x2::Cosmetic::Plant",
            "name": "Oncidium croesus",
            "data": {
                "contents": {
                    "display": "https://sui-explorer-test-image.s3.amazonaws.com/testImage.png",
                    "cosmetic_type": 1,
                    "lore": "This is a species of orchid only found in Brazil",
                    "Humidity": "High",
                    "Temperature": "Hot",
                    "Light": "Medium",
                    "Flowering Period": "Spring to early Summer",
                    "child_object_0_id": {
                        "vec": [
                            { "bytes": "ChildObjectWImage" },
                            { "bytes": "ChildObjectWBrokenImage" }
                        ]
                    }
                }
            }
        },

        {
            "id": "ChildObjectWImage",
            "category": "object",
            "owner": { "SingleOwner": "ObjectWBrokenChild" },
            "version": "1",
            "readonly": "true",
            "objType": "0x2::Cosmetic::Plant",
            "name": "Oncidium croesus",
            "data": {
                "contents": {
                    "display": "https://sui-explorer-test-image.s3.amazonaws.com/testImage.png",
                    "cosmetic_type": 1,
                    "lore": "This object has an image"
                }
            }
        },
        {
            "id": "ChildObjectWBrokenImage",
            "category": "object",
            "owner": { "SingleOwner": "ObjectWBrokenChild" },
            "version": "1",
            "readonly": "true",
            "objType": "0x2::Cosmetic::Plant",
            "name": "Oncidium croesus",
            "data": {
                "contents": {
                    "display": "https://sui-explorer-test-image.s3.amazonaws.com",
                    "cosmetic_type": 1,
                    "lore": "This object lacks an image"
                }
            }
        },
        {
            "id": "7bc832ec31709638cd8d9323e90edf332gff4389",
            "category": "object",
            "owner": {
                "SingleOwner": "0xa5e6dbcf33730ace6ec8b400ff4788c1f150ff7e"
            },
            "version": "1",
            "objType": "0x2::SuiDrop::NFT",
            "name": "Bored Ape Yacht Club #8937",
            "ethAddress": "0xBC4CA0EdA7647A8aB7C2061c2E118A18a936f13D",
            "ethTokenId": "8937",
            "data": {
                "tx_digest": "Da4vHc9IwbvOYblE8LnrVsqXwryt2Kmms+xnJ7Zx5E4=",
                "contents": {
                    "display": "https://lh3.googleusercontent.com/xcPvABPQX6sG4Wwg1FsD-ztMUZwp6NeZQLTWX1PfiWvti9cFfDXw5gxvBhg6S4B5Q4CFiZV4nWGRQnzfL0YJpL_yWVgHVZ_DOFSM=w600",
                    "background": "Orange",
                    "clothes": "Tanktop",
                    "eyes": "Holographic",
                    "fur": "Dark Brown",
                    "hat": "Cowboy Hat",
                    "mouth": "Bored Unshaven Bubblegum"
                }
            }
        },
        {
            "id": "37196de8502e6d80e6a31fba1a5d6986cc018805",
            "category": "object",
            "status": "Exists",
            "details": {
                "objectRef": {
                    "objectId": "37196de8502e6d80e6a31fba1a5d6986cc018805",
                    "version": 0,
                    "digest": "uP1J4ntsoN5bzSVEV+StOrzYNUXPFQ4hQVdLowPDYuM="
                },
                "objectType": "moveObject",
                "object": {
                    "contents": {
                        "fields": {
                            "id": {
                                "fields": {
                                    "id": {
                                        "fields": {
                                            "id": {
                                                "fields": {
                                                    "bytes": "37196de8502e6d80e6a31fba1a5d6986cc018805"
                                                },
                                                "type": "0x2::id::ID"
                                            }
                                        },
                                        "type": "0x2::id::UniqueID"
                                    },
                                    "version": 0
                                },
                                "type": "0x2::id::VersionedID"
                            },
                            "value": 100000
                        },
                        "type": "0x2::coin::Coin<0x2::sui::SUI>"
                    },
                    "owner": {
                        "AddressOwner": "3997c1099d2961e09c2a302d8e3644d6ce1237ce"
                    },
                    "tx_digest": "AAAAAAAAAAAAAAAAAAAAAAAAAAAAAAAAAAAAAAAAAAA="
                }
            }
        },
        {
            "id": "8cd943fd42810749de9e0434f01feg443hgg54v1",
            "owner": {
                "SingleOwner": "0xb6f7ecdg44841bdf7fd9c511gg5899d2g261gg8f"
            },
            "category": "object",
            "version": "5",
            "readonly": "false",
            "objType": "0x2::geniteam::Monster",
            "name": "Brown Dog",
            "data": {
                "contents": {
                    "id": {},
                    "breed": 89,
                    "monster_affinity": 2,
                    "monster_description": "surprisingly cute",
                    "monster_level": 5,
                    "monster_xp": 9900,
                    "hunger_level": 5,
                    "affection_level": 3,
                    "buddy_level": 7,
                    "display": "https://geniteam-video-images.s3.amazonaws.com/131074_0_Brown_Dog.png"
                }
            }
        },
        {
            "id": "8cd943fd42810749de9e0434f01feg443hgg54v2",
            "owner": {
                "SingleOwner": "0xb6f7ecdg44841bdf7fd9c511gg5899d2g261gg8f"
            },
            "category": "object",
            "version": "6",
            "readonly": "false",
            "objType": "0x2::geniteam::Monster",
            "name": "Brown Water Dog",
            "data": {
                "contents": {
                    "water_runes_count": 1,
                    "applied_monster_cosmetic_0_id": {
                        "vec": [
                            {
                                "bytes": "3a4e674ce2810749de9e0434f01feg443hgg54v2"
                            }
                        ]
                    },
                    "id": {},
                    "breed": 89,
                    "monster_affinity": 2,
                    "monster_description": "surprisingly cute",
                    "monster_level": 5,
                    "monster_xp": 9900,
                    "hunger_level": 5,
                    "affection_level": 3,
                    "buddy_level": 9,
                    "display": "https://geniteam-video-images.s3.amazonaws.com/131842_0_Evolved_Water_Dog_Brown.png"
                }
            }
        },
        {
            "id": "3a4e674ce2810749de9e0434f01feg443hgg54v2",
            "owner": {
                "SingleOwner": "8cd943fd42810749de9e0434f01feg443hgg54v2"
            },
            "category": "object",
            "version": "1",
            "readonly": "true",
            "objType": "0x2::geniteam::MonsterCosmetic",
            "name": "Water Rune",
            "data": {
                "contents": {
                    "id": {},
                    "display": "https://geniteam-video-images.s3.amazonaws.com/1125899906842624_Rune_Water.png"
                }
            }
        },

        {
            "id": "9de054ge53921850ef0f1545g12gfh554ihh65v1",
            "owner": {
                "SingleOwner": "0xb6f7ecdg44841bdf7fd9c511gg5899d2g261gg8f"
            },
            "category": "object",
            "version": "4",
            "readonly": "false",
            "objType": "0x2::geniteam::Monster",
            "name": "White Cat",
            "data": {
                "contents": {
                    "id": {},
                    "breed": 52,
                    "monster_affinity": 3,
                    "monster_description": "little angle feline",
                    "monster_level": 8,
                    "monster_xp": 16000,
                    "hunger_level": 2,
                    "affection_level": 8,
                    "buddy_level": 5,
                    "display": "https://geniteam-video-images.s3.amazonaws.com/65537_0_White_Cat.png"
                }
            }
        },
        {
            "id": "9de054ge53921850ef0f1545g12gfh554ihh65v2",
            "owner": {
                "SingleOwner": "0xb6f7ecdg44841bdf7fd9c511gg5899d2g261gg8f"
            },
            "category": "object",
            "version": "5",
            "readonly": "false",
            "objType": "0x2::geniteam::Monster",
            "name": "White Cat with Glasses",
            "data": {
                "contents": {
                    "id": {},
                    "breed": 52,
                    "monster_affinity": 3,
                    "monster_description": "a smart cat",
                    "monster_level": 9,
                    "monster_xp": 24000,
                    "hunger_level": 2,
                    "affection_level": 8,
                    "buddy_level": 5,
                    "applied_monster_cosmetic_0_id": {
                        "vec": [
                            {
                                "bytes": "f4a5535e53921850ef0f1545g12gfh554ihh65v2"
                            }
                        ]
                    },
                    "display": "https://geniteam-video-images.s3.amazonaws.com/4295032833_2_White_Cat_Goggles1.png"
                }
            }
        },
        {
            "id": "f4a5535e53921850ef0f1545g12gfh554ihh65v2",
            "owner": {
                "SingleOwner": "9de054ge53921850ef0f1545g12gfh554ihh65v2"
            },
            "category": "object",
            "version": "1",
            "readonly": "true",
            "objType": "0x2::geniteam::MonsterCosmetic",
            "name": "Glasses",
            "data": {
                "contents": {
                    "id": {},
                    "display": "https://geniteam-video-images.s3.amazonaws.com/4294967296_Goggles1.png"
                }
            }
        },

        {
            "id": "0ef165hf64032961fg1g2656h23hgi665jii7690",
            "owner": {
                "SingleOwner": "0xb6f7ecdg44841bdf7fd9c511gg5899d2g261gg8f"
            },
            "category": "object",
            "version": "7",
            "readonly": "false",
            "objType": "0x2::geniteam::Monster",
            "name": "White Fire Cat",
            "data": {
                "contents": {
                    "id": {},
                    "applied_monster_cosmetic_0_id": {
                        "vec": [
                            {
                                "bytes": "f14e489364032961fg1g2656h23hgi665jii7690"
                            }
                        ]
                    },
                    "breed": 55,
                    "monster_affinity": 8,
                    "monster_description": "this cat burns",
                    "monster_level": 10,
                    "monster_xp": 24000,
                    "hunger_level": 1,
                    "affection_level": 6,
                    "buddy_level": 9,
                    "fire_runes_count": 1,
                    "display": "https://geniteam-video-images.s3.amazonaws.com/66049_0_Evolved_Fire_Cat_White.png"
                }
            }
        },
        {
            "id": "f14e489364032961fg1g2656h23hgi665jii7690",
            "owner": {
                "SingleOwner": "0ef165hf64032961fg1g2656h23hgi665jii7690"
            },
            "category": "object",
            "version": "1",
            "readonly": "true",
            "objType": "0x2::geniteam::MonsterCosmetic",
            "name": "Fire Rune",
            "data": {
                "contents": {
                    "id": {},
                    "display": "https://geniteam-video-images.s3.amazonaws.com/562949953421312_Rune_Fire.png"
                }
            }
        },
        {
            "id": "Da4vHc9IwbvOYblE8LnrVsqXwryt2Kmms+xnJ7Zx5E4=",
            "category": "transaction",
            "certificate": {
                "transactionDigest": "Da4vHc9IwbvOYblE8LnrVsqXwryt2Kmms+xnJ7Zx5E4==",
                "data": {
                    "transactions": [
                        {
                            "Call": {
                                "package": {
                                    "objectId": "0x0000000000000000000000000000000000000002",
                                    "version": 1,
                                    "digest": "MBHZlAxrxXQw2ZxVa37kouRgGSI6GGK8Il5lgd5fMTM="
                                },
                                "module": "devnet_nft",
                                "function": "mint",
                                "arguments": [
                                    "Example NFT",
                                    "An NFT created by the wallet Command Line Tool",
                                    "ipfs://bafkreibngqhl3gaa7daob4i2vccziay2jjlp435cf66vhono7nrvww53ty"
                                ]
                            }
                        }
                    ],
                    "sender": "0x15090b0b58e2cffdf41f82bb79aa61d101669511",
                    "gasPayment": {
                        "objectId": "0x010669175cee34d61c4ab84a839895188ad8663d",
                        "version": 0,
                        "digest": "eUheubDSPm5tOAk/gDmSi9+ebi111/K4RphTiAq+mog="
                    },
                    "gasBudget": 10000
                },
                "txSignature": "PdUYEsl7ELW2xuBkkR2+T9LNYhYDkYyMXB9KrpWQhW1O0rqQFUnaN/zRNlG687urc0gMqqEzaB7X3z6qxnyiC8eSU1B+GYwODN677Gg4RKJsnoD9MoDgLfbD5KlmW6t0",
                "authSignInfo": {
                    "epoch": 0,
                    "signatures": [
                        "LsI1DK+7kkcMx5DWb6bxuVPtkwCP4TJAjvVw2NosuJNgtfC0w6aP7JqD4MCMm/c/FBQ/wFP3nb6yck2gy4XkAw==",
                        "2d4WcVIS3cKSnk4csYDMyZSNtE3JiYoBh+ylYfjVNrjQAIgligEkM1Msk4vRwVDoRBjHkFILGmO/SQE8UP+bCg==",
                        "ZLWlGHYGf7wCThex8Hhl+ooea20vfXKjMbq8Xg1WGWxdqwVr18JoJWa8xR6DlVS7gwDPgrVYYVr2/fqurJ3nCw=="
                    ]
                }
            },
            "effects": {
                "status": {
                    "status": "success"
                },
                "gasUsed": {
                    "computationCost": 752,
                    "storageCost": 40,
                    "storageRebate": 0
                },
                "transactionDigest": "Da4vHc9IwbvOYblE8LnrVsqXwryt2Kmms+xnJ7Zx5E4=",
                "created": [
                    {
                        "owner": {
                            "AddressOwner": "0x15090b0b58e2cffdf41f82bb79aa61d101669511"
                        },
                        "reference": {
                            "objectId": "0xd070e8251a5e094dbd7175906b24a5c1ae8d2f41",
                            "version": 1,
                            "digest": "Ra1j4fwZg/oFBcxsAFPNP8/vBx7vxhf3obkwdjW/FiE="
                        }
                    }
                ],
                "mutated": [
                    {
                        "owner": {
                            "AddressOwner": "0x15090b0b58e2cffdf41f82bb79aa61d101669511"
                        },
                        "reference": {
                            "objectId": "0x010669175cee34d61c4ab84a839895188ad8663d",
                            "version": 1,
                            "digest": "bOUPw2YiK/oRigTHfVeNOncQP1cAuchGfspKyW5QK4Q="
                        }
                    }
                ],
                "gasObject": {
                    "owner": {
                        "AddressOwner": "0x15090b0b58e2cffdf41f82bb79aa61d101669511"
                    },
                    "reference": {
                        "objectId": "0x010669175cee34d61c4ab84a839895188ad8663d",
                        "version": 1,
                        "digest": "bOUPw2YiK/oRigTHfVeNOncQP1cAuchGfspKyW5QK4Q="
                    }
                },
                "events": [
                    {
                        "moveEvent": {
                            "type": "0x2::devnet_nft::MintNFTEvent",
                            "fields": {
                                "creator": "0x15090b0b58e2cffdf41f82bb79aa61d101669511",
                                "name": "Example NFT",
                                "object_id": "0xd070e8251a5e094dbd7175906b24a5c1ae8d2f41"
                            },
                            "bcs": "0HDoJRpeCU29cXWQaySlwa6NL0EVCQsLWOLP/fQfgrt5qmHRAWaVEQtFeGFtcGxlIE5GVA=="
                        }
                    },
                    {
                        "newObject": "0xd070e8251a5e094dbd7175906b24a5c1ae8d2f41"
                    }
                ]
            },
            "timestamp_ms": 1734220800000
        },
        {
            "id": "GHTP9gcFmF5KTspnz3KxXjvSH8Bx0jv68KFhdqfpdK8=",
            "category": "transaction",
            "certificate": {
                "transactionDigest": "GHTP9gcFmF5KTspnz3KxXjvSH8Bx0jv68KFhdqfpdK8=",
                "data": {
                    "transactions": [
                        {
                            "TransferCoin": {
                                "recipient": "0x15090b0b58e2cffdf41f82bb79aa61d101669511",
                                "objectRef": {
                                    "objectId": "0x010669175cee34d61c4ab84a839895188ad8663d",
                                    "version": 4,
                                    "digest": "XyPCfS7HCdcYsQoz6IAMmftvsbCnBFBc1OJOqgXbdo8="
                                }
                            }
                        }
                    ],
                    "sender": "0x15090b0b58e2cffdf41f82bb79aa61d101669511",
                    "gasPayment": {
                        "objectId": "0x0764893d8839dc3d45ad5c13f44051e1f23b4543",
                        "version": 1,
                        "digest": "fD2JhRU1rjLv8A3C/AGZZ1JkwYyVUpLmOpXaj71j7fc="
                    },
                    "gasBudget": 1000
                },
                "txSignature": "SWQ7hAuhkrky4Kxq0lfelPz8NfWr9IbpyBp4gcnULBjzw+G+t/l0pM0fNtNbXmSGo4GIXW6uHirlT9eiZcJnAMeSU1B+GYwODN677Gg4RKJsnoD9MoDgLfbD5KlmW6t0",
                "authSignInfo": {
                    "epoch": 0,
                    "signatures": [
                        "6R+WxlZ80e53aRxr0R44Kzz9xVm3+0WgvuRYp43Z3BNrUYVfPX8kEVIjwGQ/5JCs5IbzKQh2TR+Geazj6LLwAg==",
                        "DvKi7uns1j97P2/U/ZjsGoBa9n413AXKRa/zyzKZlzpc3vvF90kN4U96DSQIH+OS5MMWGD1eI0Z0EaYRiVzsAg==",
                        "rWUlaHfK+fKKyGjzEgfQoKhxRf175JnPevX0IVa5kUxgpdGiMhSRCJ2ZIWpnfDwlRJQdQrWBkovW2JzNycVsCA=="
                    ]
                }
            },
            "effects": {
                "status": {
                    "status": "success"
                },
                "gasUsed": {
                    "computationCost": 41,
                    "storageCost": 30,
                    "storageRebate": 30
                },
                "transactionDigest": "GHTP9gcFmF5KTspnz3KxXjvSH8Bx0jv68KFhdqfpdK8=",
                "mutated": [
                    {
                        "owner": {
                            "AddressOwner": "0x15090b0b58e2cffdf41f82bb79aa61d101669511"
                        },
                        "reference": {
                            "objectId": "0x010669175cee34d61c4ab84a839895188ad8663d",
                            "version": 5,
                            "digest": "0B/JlRHInDJropiw7pfxr+vC2db3e36n8J1q7PAzVxU="
                        }
                    },
                    {
                        "owner": {
                            "AddressOwner": "0x15090b0b58e2cffdf41f82bb79aa61d101669511"
                        },
                        "reference": {
                            "objectId": "0x0764893d8839dc3d45ad5c13f44051e1f23b4543",
                            "version": 2,
                            "digest": "IhBc37sW+NffXOy9DFZCRuploq29WCUELxkWCfXxr2M="
                        }
                    }
                ],
                "gasObject": {
                    "owner": {
                        "AddressOwner": "0x15090b0b58e2cffdf41f82bb79aa61d101669511"
                    },
                    "reference": {
                        "objectId": "0x0764893d8839dc3d45ad5c13f44051e1f23b4543",
                        "version": 2,
                        "digest": "IhBc37sW+NffXOy9DFZCRuploq29WCUELxkWCfXxr2M="
                    }
                },
                "events": [
                    {
                        "transferObject": {
                            "objectId": "0x010669175cee34d61c4ab84a839895188ad8663d",
                            "version": 5,
                            "destinationAddr": "0x15090b0b58e2cffdf41f82bb79aa61d101669511",
                            "type": "Coin"
                        }
                    }
                ],
                "dependencies": ["jaqy0PGgFgUxrAPhLwJONJXSakmr6noURHnC/aw0f5U="]
            },
            "timestamp_ms": 1735693927000
        },
        {
            "id": "XHTP9gcFmF5KTspnz3KxXjvSH8Bx0jv68KFhdqfpdK8=",
            "category": "transaction",
            "certificate": {
                "authSignInfo": {
                    "epoch": 0,
                    "signatures": [
                        "PlOlGgEpHkq40F8Z8kdcze0diuNKuLCOCR41SIbv3ePBYZF/EHmJDnDzFbqdnCEqRGTbKeWdi8+GOlgqJ2O4Bg==",
                        "VVIuzJzLJQ91Dsr/IVclhDHlV3kyBGUqUcBLMiFawhimhZNjq476y5ERb42E9fmftTFOeoRl3J9/KEWmq3J8Dg==",
                        "HcfTrhvCqBqRXNL2FqI91JXbzFn1BsGUIO3jc7sQSKQP62fe4+orJFHjvYVHcLAJHURrn4R7bpXr6XsTbdc/DQ=="
                    ]
                },
                "data": {
                    "gasBudget": 100,
                    "gasPayment": {
                        "digest": "Ym6IRfWa3oGdzpFdDEd31t8vnRCdr0wUOtD+JZKB5J4=",
                        "objectId": "0x010669175cee34d61c4ab84a839895188ad8663d",
                        "version": 6
                    },
                    "sender": "0x15090b0b58e2cffdf41f82bb79aa61d101669511",
                    "transactions": [
                        {
                            "Call": {
                                "function": "new_game",
                                "module": "hero",
                                "package": {
                                    "digest": "dHbLXGi+STbi4MWeOTriSBTKV87eEpML7897PlUms1A=",
                                    "objectId": "0xf581c6835de6ab63ee108e9b679e511a1d4d6437",
                                    "version": 1
                                }
                            }
                        }
                    ]
                },
                "transactionDigest": "XHTP9gcFmF5KTspnz3KxXjvSH8Bx0jv68KFhdqfpdK8=",
                "txSignature": "Y3X++bqv5yvddzOUygdsx0DkneU4R+Pwqln6W1UA890o7ODKf7SN8T1UDdyVI3CFJxgW4KY3qpHRlqb3qkylCceSU1B+GYwODN677Gg4RKJsnoD9MoDgLfbD5KlmW6t0"
            },
            "effects": {
                "dependencies": [
                    "vYgXFyeB622QtChqaxZTO4V0edCOnJnExdCalbETkBQ=",
                    "6XIKoAQMDf18bl0Cj8M8xoBEBad054UqC4IBMSN/jA0="
                ],
                "gasObject": {
                    "owner": {
                        "AddressOwner": "0x15090b0b58e2cffdf41f82bb79aa61d101669511"
                    },
                    "reference": {
                        "digest": "v0PfepwbOOf+wga/jqQ/dhfYs6sWbqYmMImDVqmIsT8=",
                        "objectId": "0x010669175cee34d61c4ab84a839895188ad8663d",
                        "version": 7
                    }
                },
                "gasUsed": {
                    "computationCost": 100,
                    "storageCost": 0,
                    "storageRebate": 0
                },
                "mutated": [
                    {
                        "owner": {
                            "AddressOwner": "0x15090b0b58e2cffdf41f82bb79aa61d101669511"
                        },
                        "reference": {
                            "digest": "v0PfepwbOOf+wga/jqQ/dhfYs6sWbqYmMImDVqmIsT8=",
                            "objectId": "0x010669175cee34d61c4ab84a839895188ad8663d",
                            "version": 7
                        }
                    }
                ],
                "status": {
                    "error": "InsufficientGas",
                    "status": "failure"
                },
                "transactionDigest": "XHTP9gcFmF5KTspnz3KxXjvSH8Bx0jv68KFhdqfpdK8="
            },
            "timestamp_ms": 1735693989999
        }
    ]
}
